LICENSE
MANIFEST.in
README.rst
setup.py
gears_coffeescript/__init__.py
gears_coffeescript/compiler.js
gears_coffeescript/compiler.py
gears_coffeescript.egg-info/PKG-INFO
gears_coffeescript.egg-info/SOURCES.txt
gears_coffeescript.egg-info/dependency_links.txt
gears_coffeescript.egg-info/top_level.txt
gears_coffeescript/node_modules/coffee-script/.npmignore
gears_coffeescript/node_modules/coffee-script/CNAME
gears_coffeescript/node_modules/coffee-script/CONTRIBUTING.md
gears_coffeescript/node_modules/coffee-script/LICENSE
gears_coffeescript/node_modules/coffee-script/README
gears_coffeescript/node_modules/coffee-script/package.json
gears_coffeescript/node_modules/coffee-script/register.js
gears_coffeescript/node_modules/coffee-script/bin/cake
gears_coffeescript/node_modules/coffee-script/bin/coffee
gears_coffeescript/node_modules/coffee-script/lib/coffee-script/browser.js
gears_coffeescript/node_modules/coffee-script/lib/coffee-script/cake.js
gears_coffeescript/node_modules/coffee-script/lib/coffee-script/coffee-script.js
gears_coffeescript/node_modules/coffee-script/lib/coffee-script/command.js
gears_coffeescript/node_modules/coffee-script/lib/coffee-script/grammar.js
gears_coffeescript/node_modules/coffee-script/lib/coffee-script/helpers.js
gears_coffeescript/node_modules/coffee-script/lib/coffee-script/index.js
gears_coffeescript/node_modules/coffee-script/lib/coffee-script/lexer.js
gears_coffeescript/node_modules/coffee-script/lib/coffee-script/nodes.js
gears_coffeescript/node_modules/coffee-script/lib/coffee-script/optparse.js
gears_coffeescript/node_modules/coffee-script/lib/coffee-script/parser.js
gears_coffeescript/node_modules/coffee-script/lib/coffee-script/register.js
gears_coffeescript/node_modules/coffee-script/lib/coffee-script/repl.js
gears_coffeescript/node_modules/coffee-script/lib/coffee-script/rewriter.js
gears_coffeescript/node_modules/coffee-script/lib/coffee-script/scope.js
gears_coffeescript/node_modules/coffee-script/lib/coffee-script/sourcemap.js
gears_coffeescript/node_modules/coffee-script/node_modules/mkdirp/.npmignore
gears_coffeescript/node_modules/coffee-script/node_modules/mkdirp/.travis.yml
